Metadata-Version: 2.4
Name: isat-plugin-auto-annotate
Version: 1.1.1
Summary: ISAT Plugin for auto annotate by yolo detect model.
Home-page: https://github.com/yatengLG/ISAT_plugin_auto_annotate
Author: yatengLG
Author-email: yatenglg@foxmail.com
License: Apache2.0
Keywords: isat-sam,isat plugin,auto annotate
Classifier: Intended Audience :: Developers
Classifier: Intended Audience :: Science/Research
Classifier: Development Status :: 5 - Production/Stable
Classifier: Natural Language :: Chinese (Simplified)
Classifier: Natural Language :: English
Classifier: License :: OSI Approved :: Apache Software License
Classifier: Operating System :: OS Independent
Classifier: Programming Language :: Python
Classifier: Programming Language :: Python :: 3.8
Classifier: Programming Language :: Python :: 3.9
Classifier: Programming Language :: Python :: 3.10
Requires-Python: >=3.8
Requires-Dist: isat-sam>=1.4.0
Requires-Dist: onnxruntime
Dynamic: author
Dynamic: author-email
Dynamic: classifier
Dynamic: description
Dynamic: description-content-type
Dynamic: home-page
Dynamic: keywords
Dynamic: license
Dynamic: requires-dist
Dynamic: requires-python
Dynamic: summary
